LICENSE
pyokx/__init__.py
pyokx/account.py
pyokx/auth.py
pyokx/base.py
pyokx/block_trading.py
pyokx/constants.py
pyokx/convert.py
pyokx/copy_trading.py
pyokx/earn.py
pyokx/exceptions.py
pyokx/funding.py
pyokx/grid_trading.py
pyokx/market_data.py
pyokx/public_data.py
pyokx/recurring_buy.py
pyokx/savings.py
pyokx/status.py
pyokx/subaccount.py
pyokx/tests/__init__.py
pyokx/tests/test_auth.py
pyokx/tests/test_base.py
pyokx/trade.py
pyokx/trading_data.py
pyokx-0.7.0.dist-info/METADATA
pyokx-0.7.0.dist-info/WHEEL
pyokx-0.7.0.dist-info/LICENSE
pyokx-0.7.0.dist-info/RECORD
